<?xml version="1.0" encoding="utf-8"?>
	<annotation>
		<folder>driving_annotation_dataset</folder>
		<filename>31_Waiter_Waitress_Waiter_Waitress_31_372.jpg</filename>
		<size>
			<width>1024</width>
			<height>768</height>
			<depth>3</depth>
		</size>
		<object>
			<name>nomask</name>
			<pose>Unspecified</pose>
			<truncated>0</truncated>
			<difficult>0</difficult>
			<bndbox>
				<xmin>284</xmin>
				<ymin>461</ymin>
				<xmax>316</xmax>
				<ymax>503</ymax>
			</bndbox>
		</object>
		<object>
			<name>nomask</name>
			<pose>Unspecified</pose>
			<truncated>0</truncated>
			<difficult>0</difficult>
			<bndbox>
				<xmin>130</xmin>
				<ymin>517</ymin>
				<xmax>159</xmax>
				<ymax>549</ymax>
			</bndbox>
		</object>
		<object>
			<name>nomask</name>
			<pose>Unspecified</pose>
			<truncated>0</truncated>
			<difficult>0</difficult>
			<bndbox>
				<xmin>610</xmin>
				<ymin>533</ymin>
				<xmax>625</xmax>
				<ymax>552</ymax>
			</bndbox>
		</object>
		<object>
			<name>nomask</name>
			<pose>Unspecified</pose>
			<truncated>0</truncated>
			<difficult>0</difficult>
			<bndbox>
				<xmin>648</xmin>
				<ymin>539</ymin>
				<xmax>664</xmax>
				<ymax>558</ymax>
			</bndbox>
		</object>
	</annotation>
