<?xml version="1.0" encoding="utf-8"?>
	<annotation>
		<folder>driving_annotation_dataset</folder>
		<filename>32_Worker_Laborer_Worker_Laborer_32_970.jpg</filename>
		<size>
			<width>1024</width>
			<height>711</height>
			<depth>3</depth>
		</size>
		<object>
			<name>nomask</name>
			<pose>Unspecified</pose>
			<truncated>0</truncated>
			<difficult>0</difficult>
			<bndbox>
				<xmin>375</xmin>
				<ymin>251</ymin>
				<xmax>495</xmax>
				<ymax>425</ymax>
			</bndbox>
		</object>
	</annotation>
