<?xml version="1.0" encoding="utf-8"?>
	<annotation>
		<folder>driving_annotation_dataset</folder>
		<filename>51_Dresses_wearingdress_51_100.jpg</filename>
		<size>
			<width>1024</width>
			<height>1535</height>
			<depth>3</depth>
		</size>
		<object>
			<name>nomask</name>
			<pose>Unspecified</pose>
			<truncated>0</truncated>
			<difficult>0</difficult>
			<bndbox>
				<xmin>378</xmin>
				<ymin>130</ymin>
				<xmax>554</xmax>
				<ymax>359</ymax>
			</bndbox>
		</object>
		<object>
			<name>nomask</name>
			<pose>Unspecified</pose>
			<truncated>0</truncated>
			<difficult>0</difficult>
			<bndbox>
				<xmin>628</xmin>
				<ymin>729</ymin>
				<xmax>658</xmax>
				<ymax>766</ymax>
			</bndbox>
		</object>
		<object>
			<name>nomask</name>
			<pose>Unspecified</pose>
			<truncated>0</truncated>
			<difficult>0</difficult>
			<bndbox>
				<xmin>688</xmin>
				<ymin>718</ymin>
				<xmax>718</xmax>
				<ymax>755</ymax>
			</bndbox>
		</object>
	</annotation>
